LICENSE
README.md
setup.py
chatterbox_api/__init__.py
chatterbox_api/cli.py
chatterbox_api/client.py
chatterbox_server.egg-info/PKG-INFO
chatterbox_server.egg-info/SOURCES.txt
chatterbox_server.egg-info/dependency_links.txt
chatterbox_server.egg-info/entry_points.txt
chatterbox_server.egg-info/requires.txt
chatterbox_server.egg-info/top_level.txt